odoo/addons/product_medical/README.rst
odoo/addons/product_medical/__init__.py
odoo/addons/product_medical/__manifest__.py
odoo/addons/product_medical/data/in_vitro_diagnostic_data.xml
odoo/addons/product_medical/data/medical_data.xml
odoo/addons/product_medical/data/medicine_category_data.xml
odoo/addons/product_medical/data/ppe_category_data.xml
odoo/addons/product_medical/i18n/ca.po
odoo/addons/product_medical/i18n/de.po
odoo/addons/product_medical/i18n/es.po
odoo/addons/product_medical/i18n/it.po
odoo/addons/product_medical/i18n/product_medical.pot
odoo/addons/product_medical/migrations/18.0.1.0.0/pre-migrate.py
odoo/addons/product_medical/models/__init__.py
odoo/addons/product_medical/models/in_vitro_diagnostic.py
odoo/addons/product_medical/models/medical_category.py
odoo/addons/product_medical/models/medical_class.py
odoo/addons/product_medical/models/ppe_category.py
odoo/addons/product_medical/models/product_template.py
odoo/addons/product_medical/readme/CONTRIBUTORS.md
odoo/addons/product_medical/readme/CREDITS.md
odoo/addons/product_medical/readme/DESCRIPTION.md
odoo/addons/product_medical/security/ir.model.access.csv
odoo/addons/product_medical/static/description/icon.png
odoo/addons/product_medical/static/description/index.html
odoo/addons/product_medical/views/in_vitro_diagnostic.xml
odoo/addons/product_medical/views/medical_class.xml
odoo/addons/product_medical/views/medicine_category.xml
odoo/addons/product_medical/views/ppe_category.xml
odoo/addons/product_medical/views/product_template.xml
odoo_addon_product_medical-18.0.1.0.0.4.dist-info/METADATA
odoo_addon_product_medical-18.0.1.0.0.4.dist-info/WHEEL
odoo_addon_product_medical-18.0.1.0.0.4.dist-info/top_level.txt
odoo_addon_product_medical-18.0.1.0.0.4.dist-info/RECORD
